MANIFEST.in
setup.py
zjkdemo3/__init__.py
zjkdemo3/_version.py
zjkdemo3/argument_utility.py
zjkdemo3/base.py
zjkdemo3/cli.py
zjkdemo3/constants.py
zjkdemo3/containers.py
zjkdemo3/context.py
zjkdemo3/dataset.cpp
zjkdemo3/datasets.py
zjkdemo3/decorators.py
zjkdemo3/gpu.py
zjkdemo3/itertools.py
zjkdemo3/logger.py
zjkdemo3/torch_utility.py
zjkdemo3.egg-info/PKG-INFO
zjkdemo3.egg-info/SOURCES.txt
zjkdemo3.egg-info/dependency_links.txt
zjkdemo3.egg-info/entry_points.txt
zjkdemo3.egg-info/not-zip-safe
zjkdemo3.egg-info/requires.txt
zjkdemo3.egg-info/top_level.txt
zjkdemo3/build/__init__.py
zjkdemo3/d3rlpy/algos/__init__.py
zjkdemo3/d3rlpy/algos/awac.py
zjkdemo3/d3rlpy/algos/awr.py
zjkdemo3/d3rlpy/algos/base.py
zjkdemo3/d3rlpy/algos/bc.py
zjkdemo3/d3rlpy/algos/bcq.py
zjkdemo3/d3rlpy/algos/bear.py
zjkdemo3/d3rlpy/algos/combo.py
zjkdemo3/d3rlpy/algos/cql.py
zjkdemo3/d3rlpy/algos/crr.py
zjkdemo3/d3rlpy/algos/ddpg.py
zjkdemo3/d3rlpy/algos/dqn.py
zjkdemo3/d3rlpy/algos/mopo.py
zjkdemo3/d3rlpy/algos/plas.py
zjkdemo3/d3rlpy/algos/random_policy.py
zjkdemo3/d3rlpy/algos/sac.py
zjkdemo3/d3rlpy/algos/td3.py
zjkdemo3/d3rlpy/algos/td3_plus_bc.py
zjkdemo3/d3rlpy/algos/utility.py
zjkdemo3/d3rlpy/algos/torch/__init__.py
zjkdemo3/d3rlpy/algos/torch/awac_impl.py
zjkdemo3/d3rlpy/algos/torch/awr_impl.py
zjkdemo3/d3rlpy/algos/torch/base.py
zjkdemo3/d3rlpy/algos/torch/bc_impl.py
zjkdemo3/d3rlpy/algos/torch/bcq_impl.py
zjkdemo3/d3rlpy/algos/torch/bear_impl.py
zjkdemo3/d3rlpy/algos/torch/combo_impl.py
zjkdemo3/d3rlpy/algos/torch/cql_impl.py
zjkdemo3/d3rlpy/algos/torch/crr_impl.py
zjkdemo3/d3rlpy/algos/torch/ddpg_impl.py
zjkdemo3/d3rlpy/algos/torch/dqn_impl.py
zjkdemo3/d3rlpy/algos/torch/plas_impl.py
zjkdemo3/d3rlpy/algos/torch/sac_impl.py
zjkdemo3/d3rlpy/algos/torch/td3_impl.py
zjkdemo3/d3rlpy/algos/torch/td3_plus_bc_impl.py
zjkdemo3/d3rlpy/algos/torch/utility.py
zjkdemo3/d3rlpy/dynamics/__init__.py
zjkdemo3/d3rlpy/dynamics/base.py
zjkdemo3/d3rlpy/dynamics/probabilistic_ensemble_dynamics.py
zjkdemo3/d3rlpy/dynamics/torch/__init__.py
zjkdemo3/d3rlpy/dynamics/torch/base.py
zjkdemo3/d3rlpy/dynamics/torch/probabilistic_ensemble_dynamics_impl.py
zjkdemo3/d3rlpy/envs/__init__.py
zjkdemo3/d3rlpy/envs/batch.py
